ncmi_idc_extract_interfaces/__init__.py
ncmi_idc_extract_interfaces/api_models.py
ncmi_idc_extract_interfaces/models.py
ncmi_idc_extract_interfaces/py.typed
ncmi_idc_extract_interfaces/query_models.py
ncmi_idc_extract_interfaces-1.2.7.dist-info/WHEEL
ncmi_idc_extract_interfaces-1.2.7.dist-info/METADATA
ncmi_idc_extract_interfaces-1.2.7.dist-info/RECORD
