Metadata-Version: 2.4
Name: ncmi-idc-extract-interfaces
Version: 1.2.7
Author: Petridis, Ross (NCMI, Hobart)
Author-email: Petridis, Ross (NCMI, Hobart) <Ross.Petridis@csiro.au>
License-Expression: MIT
Requires-Dist: pydantic>=2.0.0,<=3.0.0
Requires-Dist: pydantic-settings
Requires-Dist: pydantic[email]
Requires-Python: >=3.10, <3.14
